<?xml version="1.0" encoding="UTF-8"?>
<jcr:root xmlns:sling="http://sling.apache.org/jcr/sling/1.0" xmlns:cq="http://www.day.com/jcr/cq/1.0" xmlns:jcr="http://www.jcp.org/jcr/1.0" xmlns:nt="http://www.jcp.org/jcr/nt/1.0"
    jcr:primaryType="nt:unstructured"
    jcr:title="Footer"
    sling:resourceType="cq/gui/components/authoring/dialog">
    <content
        jcr:primaryType="nt:unstructured"
        sling:resourceType="granite/ui/components/coral/foundation/container">
        <items jcr:primaryType="nt:unstructured">
            <tabs
                jcr:primaryType="nt:unstructured"
                sling:resourceType="granite/ui/components/coral/foundation/tabs"
                maximized="{Boolean}true">
                <items jcr:primaryType="nt:unstructured">
                    <sociallinks
                        jcr:primaryType="nt:unstructured"
                        jcr:title="Social Links"
                        sling:resourceType="granite/ui/components/coral/foundation/container"
                        margin="{Boolean}true">
                        <items jcr:primaryType="nt:unstructured">
                            <columns
                                jcr:primaryType="nt:unstructured"
                                sling:resourceType="granite/ui/components/coral/foundation/fixedcolumns"
                                margin="{Boolean}true">
                                <items jcr:primaryType="nt:unstructured">
                                    <column
                                        jcr:primaryType="nt:unstructured"
                                        sling:resourceType="granite/ui/components/coral/foundation/container">
                                        <items jcr:primaryType="nt:unstructured">
                                            <socialfooter
                                                jcr:primaryType="nt:unstructured"
                                                sling:resourceType="granite/ui/components/coral/foundation/form/multifield"
                                                composite="{Boolean}true"
                                                fieldLabel="Social Footer">
                                                <field
                                                    jcr:primaryType="nt:unstructured"
                                                    sling:resourceType="granite/ui/components/coral/foundation/container"
                                                    name="./socialFooter">
                                                    <items jcr:primaryType="nt:unstructured">
                                                        <column
                                                            jcr:primaryType="nt:unstructured"
                                                            sling:resourceType="granite/ui/components/coral/foundation/container">
                                                            <items jcr:primaryType="nt:unstructured">
                                                                <image
                                                                    jcr:primaryType="nt:unstructured"
                                                                    sling:resourceType="granite/ui/components/coral/foundation/form/pathfield"
                                                                    fieldDescription="Select image."
                                                                    fieldLabel="Image"
                                                                    name="./image"
                                                                    rootPath="/content/dam/nirvana"/>
                                                                <link
                                                                    jcr:primaryType="nt:unstructured"
                                                                    sling:resourceType="granite/ui/components/coral/foundation/form/pathfield"
                                                                    fieldDescription="Select Path"
                                                                    fieldLabel="Link"
                                                                    name="./link"
                                                                    rootPath="/content/nirvana"/>
                                                                <openinnewtab
                                                                    jcr:primaryType="nt:unstructured"
                                                                    sling:resourceType="granite/ui/components/coral/foundation/form/checkbox"
                                                                    fieldDescription="Open In New Tab?"
                                                                    name="./openInNewTab"
                                                                    text="Open In New Tab?"
                                                                    uncheckedValue="false"
                                                                    value="true"/>
                                                            </items>
                                                        </column>
                                                    </items>
                                                </field>
                                            </socialfooter>
                                        </items>
                                    </column>
                                </items>
                            </columns>
                        </items>
                    </sociallinks>
                    <ourlocation
                        jcr:primaryType="nt:unstructured"
                        jcr:title="Our Location"
                        sling:resourceType="granite/ui/components/coral/foundation/container"
                        margin="{Boolean}true">
                        <items jcr:primaryType="nt:unstructured">
                            <columns
                                jcr:primaryType="nt:unstructured"
                                sling:resourceType="granite/ui/components/coral/foundation/fixedcolumns"
                                margin="{Boolean}true">
                                <items jcr:primaryType="nt:unstructured">
                                    <column
                                        jcr:primaryType="nt:unstructured"
                                        sling:resourceType="granite/ui/components/coral/foundation/container">
                                        <items jcr:primaryType="nt:unstructured">
                                            <iconimage
                                                jcr:primaryType="nt:unstructured"
                                                sling:resourceType="granite/ui/components/coral/foundation/form/pathfield"
                                                fieldLabel="Icon"
                                                name="./icon"
                                                rootPath="/content/dam/nirvana"/>
                                        </items>
                                    </column>
                                </items>
                            </columns>
                        </items>
                    </ourlocation>
                </items>
            </tabs>
        </items>
    </content>
</jcr:root>
